advertools/__init__.py
advertools/_regex_helpers.py
advertools/_yt_helpers.py
advertools/ad_create.py
advertools/ad_from_string.py
advertools/cli.py
advertools/crawlytics.py
advertools/emoji.py
advertools/extract.py
advertools/header_spider.py
advertools/image_spider.py
advertools/knowledge_graph.py
advertools/kw_generate.py
advertools/logs.py
advertools/partition.py
advertools/regex.py
advertools/reverse_dns_lookup.py
advertools/robotstxt.py
advertools/serp.py
advertools/sitemaps.py
advertools/spider.py
advertools/stopwords.py
advertools/twitter.py
advertools/url_builders.py
advertools/urlytics.py
advertools/word_frequency.py
advertools/word_tokenize.py
advertools/youtube.py
advertools/.ruff_cache/.gitignore
advertools/.ruff_cache/CACHEDIR.TAG
advertools/.ruff_cache/0.3.4/2783138099748158302
advertools/cli_docs/__init__.py
advertools/cli_docs/cli.py
advertools/code_recipes/__init__.py
advertools/code_recipes/spider_strategies.py
advertools/pkg_data/emoji_df.parquet
advertools-0.17.1.data/data/emoji_df.parquet
advertools-0.17.1.dist-info/entry_points.txt
advertools-0.17.1.dist-info/licenses/LICENSE
advertools-0.17.1.dist-info/WHEEL
advertools-0.17.1.dist-info/METADATA
advertools-0.17.1.dist-info/RECORD
