Metadata-Version: 2.4
Name: advertools
Version: 0.17.1
Summary: Digital Marketing productivity and analysis tools.
Keywords: seo,marketing,advertising,adwords,bingads,search-engine-marketing,online-marketing,digital-marketing,digital-advertising,keywords
Author-email: Elias Dabbas <eliasdabbas@gmail.com>
Classifier: License :: OSI Approved :: MIT License
Classifier: Programming Language :: Python :: 3
License-File: LICENSE
Requires-Dist: pandas>=1.1.0
Requires-Dist: pyasn1>=0.4
Requires-Dist: scrapy>=2.5.0
Requires-Dist: twython>=3.8.0
Requires-Dist: pyarrow>=5.0.0
Requires-Dist: requests>=2.25.0
Project-URL: Changelog, https://github.com/eliasdabbas/advertools/blob/master/HISTORY.rst
Project-URL: Documentation, https://advertools.readthedocs.io
Project-URL: Homepage, https://adver.tools
Project-URL: Issues, https://github.com/eliasdabbas/advertools/issues
Project-URL: Repository, https://github.com/eliasdabbas/advertools.git
